MANIFEST.in
README.rst
README.txt
distribute_setup.py
setup.py
screp/__init__.py
screp/actiondir.py
screp/anchor.py
screp/context.py
screp/format_parsers.py
screp/formatter.py
screp/idloc.py
screp/main.py
screp/source.py
screp/term.py
screp/term_parser.py
screp/termactions.py
screp/utils.py
screp.egg-info/PKG-INFO
screp.egg-info/SOURCES.txt
screp.egg-info/dependency_links.txt
screp.egg-info/entry_points.txt
screp.egg-info/namespace_packages.txt
screp.egg-info/not-zip-safe
screp.egg-info/requires.txt
screp.egg-info/top_level.txt