Metadata-Version: 1.1
Name: screp
Version: 0.3.2
Summary: Command-line utility for easy scraping of HTML documents
Home-page: https://github.com/darfire/screp
Author: Doru Arfire
Author-email: doruarfire@gmail.com
License: LGPL
Platform: UNKNOWN
Classifier: License :: OSI Approved
Classifier: License :: OSI Approved :: GNU Library or Lesser General Public License (LGPL)
Classifier: Programming Language :: Python
Classifier: Intended Audience :: Developers
Classifier: Intended Audience :: System Administrators
Classifier: Development Status :: 4 - Beta
Classifier: Environment :: Console
Classifier: Topic :: Internet :: WWW/HTTP
